drjit/__init__.py
drjit/config.py
drjit/const.py
drjit/detail.py
drjit/drjit-autodiff.dll
drjit/drjit-autodiff.lib
drjit/drjit-core.dll
drjit/drjit-core.lib
drjit/drjit_ext.cp310-win_amd64.pyd
drjit/generic.py
drjit/matrix.py
drjit/nanothread.dll
drjit/nanothread.lib
drjit/router.py
drjit/tensor.py
drjit/traits.py
psdr_jit/__init__.py
psdr_jit/drjit-autodiff.dll
psdr_jit/drjit-autodiff.lib
psdr_jit/drjit-core.dll
psdr_jit/drjit-core.lib
psdr_jit/nanothread.dll
psdr_jit/nanothread.lib
psdr_jit/psdr_jit.cp310-win_amd64.pyd
psdr_jit-0.2.1.dist-info/METADATA
psdr_jit-0.2.1.dist-info/WHEEL
psdr_jit-0.2.1.dist-info/RECORD
