Metadata-Version: 2.1
Name: psdr_jit
Version: 0.2.1
Summary: Path-space differentiable renderer with drjit as the numerical backend.
Requires-Python: >=3.8
